{
  "pensamentos": [
    {
      "conteudo": "A imaginação é mais importante que o conhecimento, porque o conhecimento é limitado, ao passo que a imaginação abrange o mundo inteiro.",
      "autoria": "Edward",
      "modelo": "modelo3",
      "id": 4
    },
    {
      "conteudo": "A imaginação é mais importante que o conhecimento, porque o conhecimento é limitado, ao passo que a imaginação abrange o mundo inteiro.",
      "autoria": "Albert Einstein ",
      "modelo": "modelo2",
      "id": 5
    },
    {
      "conteudo": "É preferível suportar os males que temos do que voar para aqueles que não conhecemos.",
      "autoria": "William Shakespeare",
      "modelo": "modelo3",
      "id": 8
    }
  ]
}